boco/CorpusBuilder.py
boco/__init__.py
boco/filters/__init__.py
boco/filters/filter_by_pos.py
boco/filters/filter_by_unique.py
boco/operations/__init__.py
boco/operations/counts_by_segment.py
boco/operations/counts_by_token.py
boco/operations/search_string.py
boco/operations/search_token.py
boco/utils/__init__.py
boco/utils/_add_pos.py
Boco-0.3.2.dist-info/METADATA
Boco-0.3.2.dist-info/WHEEL
Boco-0.3.2.dist-info/top_level.txt
Boco-0.3.2.dist-info/RECORD
